fastread/__init__.py
fastread/core.py
fastread-0.1.0.dist-info/DESCRIPTION.rst
fastread-0.1.0.dist-info/METADATA
fastread-0.1.0.dist-info/RECORD
fastread-0.1.0.dist-info/WHEEL
fastread-0.1.0.dist-info/metadata.json
fastread-0.1.0.dist-info/top_level.txt
tests/__init__.py
tests/test_fastread_class.py
